shioaji_realtime_kbars/__init__.py
shioaji_realtime_kbars/shioaji_realtime_kbars.py
shioaji_realtime_kbars-1.1.0.dist-info/LICENSE
shioaji_realtime_kbars-1.1.0.dist-info/METADATA
shioaji_realtime_kbars-1.1.0.dist-info/WHEEL
shioaji_realtime_kbars-1.1.0.dist-info/top_level.txt
shioaji_realtime_kbars-1.1.0.dist-info/RECORD
