Metadata-Version: 2.1
Name: shioaji_realtime_kbars
Version: 1.1.0
Summary: An Extensions help you streaming with real-time data
Home-page: https://github.com/NickLin910221/Shioaji_Realtime_Kline
Author: NickLin910221
Author-email: nicklin910221@gmail.com
Project-URL: Bug Tracker, https://github.com/NickLin910221/Shioaji_Realtime_Kline/issues
Keywords: shioaji
Classifier: Programming Language :: Python :: 3
Classifier: License :: OSI Approved :: MIT License
Classifier: Operating System :: OS Independent
Requires-Python: >=3.6
License-File: LICENSE
Requires-Dist: pandas
Requires-Dist: shioaji
Requires-Dist: numpy
